yarely/__init__.py
yarely-0.1.0.dist-info/AUTHORS.rst
yarely-0.1.0.dist-info/LICENSE
yarely-0.1.0.dist-info/METADATA
yarely-0.1.0.dist-info/WHEEL
yarely-0.1.0.dist-info/top_level.txt
yarely-0.1.0.dist-info/RECORD
