Metadata-Version: 2.1
Name: yarely
Version: 0.1.0
Summary: Yarely is an open Digital Signage Platform developed by the eCampus team at Lancaster University.
Home-page: https://github.com/opendisplays/yarely
Author: Lancaster University
Author-email: e-campus-help@lancaster.ac.uk
License: Apache Software License 2.0
Keywords: yarely digital signage
Platform: Mac OS X >= 10.6
Classifier: Development Status :: 4 - Beta
Classifier: Environment :: MacOS X :: Cocoa
Classifier: Intended Audience :: Developers
Classifier: Intended Audience :: End Users/Desktop
Classifier: License :: OSI Approved :: Apache Software License
Classifier: Natural Language :: English
Classifier: Operating System :: MacOS :: MacOS X
Classifier: Programming Language :: Python :: 3
Classifier: Programming Language :: Python :: 3.3
Classifier: Programming Language :: Python :: 3.4
Classifier: Programming Language :: Python :: 3.5
Classifier: Programming Language :: Python :: 3.6
Requires-Dist: pyserial
Requires-Dist: tornado
Requires-Dist: zmq
Requires-Dist: PyObjC
Requires-Dist: certifi
